medreaders/ACDC.py
medreaders/__init__.py
medreaders-1.0.8.dist-info/LICENSE
medreaders-1.0.8.dist-info/METADATA
medreaders-1.0.8.dist-info/WHEEL
medreaders-1.0.8.dist-info/top_level.txt
medreaders-1.0.8.dist-info/RECORD
