Metadata-Version: 2.1
Name: medreaders
Version: 1.0.8
Summary: Readers for medical imaging datasets
Home-page: https://github.com/ol-sen/medreaders
Author: Olga Senyukova
Author-email: olga.senyukova@graphics.cs.msu.ru
License: UNKNOWN
Platform: UNKNOWN
Classifier: Development Status :: 4 - Beta
Classifier: Intended Audience :: Developers
Classifier: Intended Audience :: Science/Research
Classifier: Intended Audience :: Healthcare Industry
Classifier: License :: OSI Approved :: MIT License
Classifier: Operating System :: Unix
Classifier: Programming Language :: Python :: 3
Classifier: Topic :: Scientific/Engineering :: Artificial Intelligence
Classifier: Topic :: Scientific/Engineering :: Image Recognition
Classifier: Topic :: Scientific/Engineering :: Medical Science Apps.
Classifier: Topic :: Software Development :: Libraries :: Python Modules
Requires-Python: >=3.5
License-File: LICENSE
Requires-Dist: imageio (>=2.3.0)
Requires-Dist: matplotlib (>=2.0.0)
Requires-Dist: nibabel (>=2.4.0)
Requires-Dist: numpy (>=1.13.3)
Requires-Dist: scikit-image (>=0.15.0)
